{
  "word": "beside",
  "phonetics": {
    "british": "/bɪˈsaɪd/",
    "american": "/bɪˈsaɪd/"
  },
  "definitions": [
    {
      "partOfSpeech": "preposition",
      "definition": "next to or at the side of someone or something",
      "chineseTranslation": "在……旁边或一旁",
      "level": "intermediate",
      "frequency": "high",
      "register": "neutral"
    },
    {
      "partOfSpeech": "preposition",
      "definition": "compared with or in comparison to",
      "chineseTranslation": "与……相比",
      "level": "intermediate",
      "frequency": "medium",
      "register": "formal"
    },
    {
      "partOfSpeech": "preposition",
      "definition": "not relevant to or aside from",
      "chineseTranslation": "与……无关或不相关",
      "level": "intermediate",
      "frequency": "medium",
      "register": "informal"
    }
  ],
  "phrases": [
    {
      "phrase": "beside the point",
      "meaning": "与主题无关",
      "example": "His comments were beside the point during the meeting.",
      "exampleTranslation": "他的评论在会议中与主题无关。",
      "frequency": "high"
    },
    {
      "phrase": "stand beside",
      "meaning": "站在旁边",
      "example": "She chose to stand beside her friend in times of trouble.",
      "exampleTranslation": "她在朋友遇到麻烦时选择站在旁边支持。",
      "frequency": "medium"
    },
    {
      "phrase": "beside oneself",
      "meaning": "极度激动或失控",
      "example": "He was beside himself with joy when he heard the news.",
      "exampleTranslation": "当他听到这个消息时，他激动得无法自已。",
      "frequency": "medium"
    }
  ],
  "examples": [
    {
      "sentence": "The book is lying beside the lamp on the table.",
      "translation": "书躺在桌上的灯旁边。",
      "source": "Daily conversation",
      "difficulty": "basic"
    },
    {
      "sentence": "Beside her accomplishments, his efforts seem minimal.",
      "translation": "与她的成就相比，他的努力显得微不足道。",
      "source": "Literary work",
      "difficulty": "intermediate"
    },
    {
      "sentence": "The argument was beside the point, as we needed to focus on the facts.",
      "translation": "这个争论与重点无关，因为我们需要关注事实。",
      "source": "News article",
      "difficulty": "advanced"
    },
    {
      "sentence": "In the garden, children played beside the old oak tree.",
      "translation": "在花园里，孩子们在老橡树旁边玩耍。",
      "source": "Fiction novel",
      "difficulty": "intermediate"
    }
  ],
  "etymology": {
    "origin": "Old English",
    "rootWords": [
      {
        "root": "be",
        "meaning": "by or near",
        "language": "Old English"
      },
      {
        "root": "sīdan",
        "meaning": "side",
        "language": "Old English"
      }
    ],
    "historicalDevelopment": "源自古英语 'be sīdan'，意思是 '在旁边'，在中古英语时期演变为现代形式，逐渐发展出比较或无关的含义，随着英语的标准化在文艺复兴时期固定下来。",
    "firstKnownUse": "约 1000 年",
    "relatedWords": [
      "besides",
      "side"
    ]
  },
  "difficultyAnalysis": {
    "overallLevel": "B1 (CEFR)",
    "pronunciationDifficulty": "3",
    "spellingDifficulty": "4",
    "meaningComplexity": "5",
    "usageComplexity": "6",
    "learningTips": [
      "结合认知科学，建议使用视觉联想法：想象一个物体放在另一个物体旁边来记忆 'beside' 的位置含义；对于初级学习者，重复上下文练习以强化语义网络，避免混淆于同音词 'besides'。"
    ]
  },
  "semanticRelations": {
    "synonyms": [
      {
        "word": "next to",
        "similarity": "0.9",
        "context": "适用于描述物理位置，如 'beside the river' 表示 '在河旁边'"
      },
      {
        "word": "alongside",
        "similarity": "0.8",
        "context": "在正式语境中用于表示并排或伴随，例如商业或社会讨论"
      }
    ],
    "antonyms": [
      {
        "word": "opposite",
        "context": "在位置语境中，表示 '在对面' 而非 '在旁边'"
      },
      {
        "word": "inside",
        "context": "表示内部而非外部位置"
      }
    ],
    "hypernyms": [
      "preposition"
    ],
    "hyponyms": [
      "next to",
      "by"
    ],
    "collocations": [
      {
        "pattern": "beside + noun",
        "examples": [
          "beside the road",
          "beside her"
        ],
        "strength": "strong"
      },
      {
        "pattern": "beside + the point",
        "examples": [
          "beside the point in arguments"
        ],
        "strength": "medium"
      }
    ]
  },
  "culturalContext": {
    "culturalSignificance": "该词在英语文化中象征空间关系，常用于文学和日常对话中隐含亲近或对比的隐喻，例如在英国文学中表示情感支持。",
    "regionalVariations": [
      {
        "region": "英国",
        "variation": "更常用于正式或文学语境",
        "usage": "在英国英语中，'beside' 可能强调传统空间描述，如在历史小说中"
      },
      {
        "region": "美国",
        "variation": "在日常口语中使用更频繁",
        "usage": "在美国英语中，常见于非正式对话，强调实用性"
      }
    ],
    "historicalContext": "与英国中世纪文学相关，如乔叟的作品中出现，反映社会阶层和物理空间的互动。",
    "modernUsage": "在社交媒体和当代对话中，'beside' 常用于表达无关性，如 'beside the point' 在在线辩论中流行，体现数字时代的信息筛选趋势。"
  },
  "memoryAids": {
    "visualScene": {
      "description": "想象一个场景：一个人站在一棵大树旁边，树代表主要物体，而人代表 'beside' 的位置。",
      "keyElements": [
        "树（主要物体）",
        "人（beside的位置）",
        "空间关系"
      ],
      "emotionalConnection": "联结个人经验，如回忆儿时在公园玩耍的场景，以触发积极情绪增强记忆"
    },
    "mnemonicDevices": [
      {
        "type": "联想",
        "content": "将 'beside' 联想为 'be side'，想象 'be' 在 'side' 旁边。",
        "explanation": "通过词根分解和视觉联想，利用认知科学中的双编码理论，将听觉和视觉信息结合以提高保留率。"
      },
      {
        "type": "缩略",
        "content": "BESIDE = By Every Side In Daily Existence",
        "explanation": "创建缩略词帮助记忆含义，基于重复曝光原则强化神经通路。"
      }
    ],
    "wordAssociations": [
      "side",
      "next",
      "by"
    ]
  },
  "grammaticalInfo": {
    "irregularForms": {
      "plural": null,
      "pastTense": null,
      "pastParticiple": null,
      "presentParticiple": null,
      "comparative": null,
      "superlative": null
    },
    "syntacticPatterns": [
      {
        "pattern": "Subject + verb + beside + object",
        "description": "介词短语结构，用于描述位置或比较。",
        "examples": [
          "The cat sat beside the fire."
        ]
      },
      {
        "pattern": "Beside + noun phrase",
        "description": "独立介词短语，常用于句子开头或中间。",
        "examples": [
          "Beside the river, we built a house."
        ]
      }
    ],
    "commonMistakes": [
      {
        "mistake": "Confusing with 'besides'",
        "correction": "Use 'beside' for location and 'besides' for addition.",
        "explanation": "二者为同音异形词，学习者常混淆；建议通过语境练习区分。"
      },
      {
        "mistake": "Incorrect preposition use",
        "correction": "Ensure it follows the correct object.",
        "explanation": "在句子中，'beside' 必须后接名词短语，以避免结构错误。"
      }
    ]
  },
  "metadata": {
    "frequency": "High (ranked in top 2000 words in COCA corpus)",
    "domains": [
      "日常对话",
      "文学",
      "教育"
    ],
    "tags": [
      "位置介词",
      "比较",
      "英语基础词汇"
    ],
    "lastUpdated": "2023-10",
    "sources": [
      "OED (Oxford English Dictionary)",
      "COCA (Corpus of Contemporary American English)",
      "BNC (British National Corpus)"
    ]
  }
}