{
  "word": "eulogistic",
  "phonetics": {
    "british": "/juːləˈdʒɪstɪk/",
    "american": "/juːləˈdʒɪstɪk/"
  },
  "definitions": [
    {
      "partOfSpeech": "adjective",
      "definition": "expressing praise and commendation, often excessively",
      "chineseTranslation": "赞美的；颂扬的，通常带有过度褒奖的意味",
      "level": "intermediate",
      "frequency": "low",
      "register": "formal"
    }
  ],
  "phrases": [
    {
      "phrase": "eulogistic speech",
      "meaning": "赞美性的演讲",
      "example": "He delivered a eulogistic speech at the awards ceremony.",
      "exampleTranslation": "他在颁奖典礼上发表了赞美性的演讲。",
      "frequency": "low"
    },
    {
      "phrase": "eulogistic review",
      "meaning": "赞美的评论",
      "example": "The book received a eulogistic review in the national newspaper.",
      "exampleTranslation": "这本书在国家报纸上获得了赞美的评论。",
      "frequency": "low"
    }
  ],
  "examples": [
    {
      "sentence": "The eulogistic biography painted the historical figure as a flawless hero.",
      "translation": "这本赞美的传记将这位历史人物描绘成完美无缺的英雄。",
      "source": "Literary biography (e.g., from a modern novel)",
      "difficulty": "intermediate"
    },
    {
      "sentence": "In her eulogistic tribute, she highlighted his contributions to society.",
      "translation": "在她的赞美悼词中，她强调了他对社会的贡献。",
      "source": "Public speech (e.g., from a memorial service)",
      "difficulty": "intermediate"
    },
    {
      "sentence": "Critics noted that the film review was overly eulogistic, lacking critical depth.",
      "translation": "评论家指出，这部电影的评论过于赞美，缺乏批判深度。",
      "source": "Film criticism (e.g., from online media)",
      "difficulty": "advanced"
    }
  ],
  "etymology": {
    "origin": "Greek, via Latin",
    "rootWords": [
      {
        "root": "eulogia",
        "meaning": "praise or commendation",
        "language": "Greek"
      },
      {
        "root": "eu-",
        "meaning": "good or well",
        "language": "Greek"
      }
    ],
    "historicalDevelopment": "源自古希腊的 'eulogia'，意为良好的话语或赞美，传入拉丁语后演变为中世纪英语中的 'eulogistic'，最初用于宗教和修辞语境，逐渐扩展到现代英语中表示正式的赞颂，强调从古典修辞到当代文学的演变",
    "firstKnownUse": "17th century",
    "relatedWords": [
      "eulogy",
      "eulogize",
      "panegyric"
    ]
  },
  "difficultyAnalysis": {
    "overallLevel": "B2",
    "pronunciationDifficulty": "5",
    "spellingDifficulty": "6",
    "meaningComplexity": "7",
    "usageComplexity": "6",
    "learningTips": [
      "结合认知科学，利用分块记忆法，将 'eulogistic' 与其词根 'eu-' (好) 联系起来，形成视觉图像，如想象一个好词的赞美场景；通过重复暴露于正式语境中增强长期记忆。"
    ]
  },
  "semanticRelations": {
    "synonyms": [
      {
        "word": "laudatory",
        "similarity": "0.8",
        "context": "在正式写作或评论中，适用于对成就的赞美"
      },
      {
        "word": "panegyric",
        "similarity": "0.7",
        "context": "在文学或历史语境中，强调高度颂扬"
      }
    ],
    "antonyms": [
      {
        "word": "critical",
        "context": "在分析性评论中，用于负面评价"
      },
      {
        "word": "derogatory",
        "context": "在争论或批评语境中，用于贬低"
      }
    ],
    "hypernyms": [
      "positive",
      "commendatory"
    ],
    "hyponyms": [
      "panegyric"
    ],
    "collocations": [
      {
        "pattern": "eulogistic + noun (e.g., speech, review)",
        "examples": [
          "eulogistic remarks",
          "eulogistic tribute"
        ],
        "strength": "medium"
      }
    ]
  },
  "culturalContext": {
    "culturalSignificance": "在西方文化中，该词常与悼念、纪念或正式赞颂相关，象征对逝者或伟人的过度理想化，可能隐含对真实性的质疑，如在 funeral eulogies 中",
    "regionalVariations": [
      {
        "region": "英国",
        "variation": "更常用于文学和学术语境",
        "usage": "在英国英语中，偏向正式场合，如文学评论，以保持传统修辞风格"
      },
      {
        "region": "美国",
        "variation": "在政治和媒体语境中更常见",
        "usage": "在美国英语中，常用于总统演讲或名人传记，以强调爱国或英雄崇拜"
      }
    ],
    "historicalContext": "与古希腊修辞学和罗马 funeral orations 相关，在文艺复兴时期传入英语，现代与文学和社会运动（如民权运动中的赞美演讲）关联",
    "modernUsage": "在社交媒体和在线评论中，趋向于讽刺使用，反映后现代对过度赞美的反讽趋势"
  },
  "memoryAids": {
    "visualScene": {
      "description": "想象一个舞台场景，演讲者手持奖杯，热情赞美一位英雄",
      "keyElements": [
        "演讲者",
        "奖杯",
        "英雄形象"
      ],
      "emotionalConnection": "联结个人经历，如回忆一次受到赞美的时刻，以触发积极情绪和记忆强化"
    },
    "mnemonicDevices": [
      {
        "type": "联想",
        "content": "Eulogistic 听起来像 'eulogy' (悼词)，都涉及赞美",
        "explanation": "通过声音和语义联想，将其与赞美场景连接，增强认知加工"
      },
      {
        "type": "缩略",
        "content": "EU-LO-GISTIC: EU for 'good' (from Greek), LO for 'praise', GISTIC for 'related'",
        "explanation": "使用首字母缩写法分解词根，便于记忆和回忆"
      }
    ],
    "wordAssociations": [
      "praise",
      "commend",
      "tribute"
    ]
  },
  "grammaticalInfo": {
    "irregularForms": {
      "plural": null,
      "pastTense": null,
      "pastParticiple": null,
      "presentParticiple": null,
      "comparative": "more eulogistic",
      "superlative": "most eulogistic"
    },
    "syntacticPatterns": [
      {
        "pattern": "be + eulogistic",
        "description": "用于描述某事物的性质，例如 'The speech was eulogistic.'",
        "examples": [
          "The article was eulogistic in tone."
        ]
      },
      {
        "pattern": "eulogistic + noun",
        "description": "用作定语修饰名词",
        "examples": [
          "a eulogistic biography"
        ]
      }
    ],
    "commonMistakes": [
      {
        "mistake": "Confusing with 'eulogy' (noun form)",
        "correction": "Use 'eulogistic' as adjective",
        "explanation": "词性混淆常见于初级学习者，确保根据语境选择正确形式"
      },
      {
        "mistake": "Overusing in informal contexts",
        "correction": "Reserve for formal registers",
        "explanation": "该词语域为正式，避免在口语中误用以保持适当语气"
      }
    ]
  },
  "metadata": {
    "frequency": "Low (e.g., ranked below 10,000 in COCA corpus)",
    "domains": [
      "Literature",
      "Politics",
      "Academia"
    ],
    "tags": [
      "Adjective",
      "Praise",
      "Formal Language"
    ],
    "lastUpdated": "2023-10",
    "sources": [
      "OED (Oxford English Dictionary)",
      "Merriam-Webster",
      "COCA (Corpus of Contemporary American English)"
    ]
  }
}