{
  "word": "grubby",
  "phonetics": {
    "british": "/ˈɡrʌbi/",
    "american": "/ˈɡrʌbi/"
  },
  "definitions": [
    {
      "partOfSpeech": "adjective",
      "definition": "Covered with dirt or grime, often as a result of use or neglect; also used to describe something shabby or unkempt.",
      "chineseTranslation": "肮脏的；邋遢的",
      "level": "intermediate",
      "frequency": "medium",
      "register": "informal"
    },
    {
      "partOfSpeech": "adjective",
      "definition": "Figuratively, mean or disreputable, as in behavior or appearance.",
      "chineseTranslation": "卑鄙的；低劣的",
      "level": "intermediate",
      "frequency": "low",
      "register": "neutral"
    }
  ],
  "phrases": [
    {
      "phrase": "grubby hands",
      "meaning": "脏兮兮的手",
      "example": "The mechanic wiped his grubby hands on a rag after fixing the engine.",
      "exampleTranslation": "修理工在修理引擎后，用抹布擦了擦他那脏兮兮的手。",
      "frequency": "medium"
    },
    {
      "phrase": "grubby clothes",
      "meaning": "肮脏的衣服",
      "example": "She refused to wear her grubby clothes to the party and changed into something clean.",
      "exampleTranslation": "她拒绝穿着那件肮脏的衣服去派对，而是换上了干净的衣服。",
      "frequency": "medium"
    },
    {
      "phrase": "grubby little secret",
      "meaning": "卑鄙的小秘密",
      "example": "Everyone has a grubby little secret they don't want to share.",
      "exampleTranslation": "每个人都有一些卑鄙的小秘密不想分享。",
      "frequency": "low"
    }
  ],
  "examples": [
    {
      "sentence": "After playing in the mud all afternoon, the children's faces were grubby and in need of a wash.",
      "translation": "孩子们在泥巴里玩耍了一整个下午，脸上变得肮脏，需要洗一洗。",
      "source": "Children's literature or everyday conversation",
      "difficulty": "intermediate"
    },
    {
      "sentence": "The old bookstore had a grubby exterior, but inside it was filled with treasures.",
      "translation": "那家旧书店外表邋遢，但里面满是珍宝。",
      "source": "Modern fiction",
      "difficulty": "intermediate"
    },
    {
      "sentence": "In the detective novel, the suspect's grubby appearance made him seem more suspicious.",
      "translation": "在侦探小说中，嫌疑人邋遢的外表让他显得更加可疑。",
      "source": "Literary works",
      "difficulty": "advanced"
    }
  ],
  "etymology": {
    "origin": "English",
    "rootWords": [
      {
        "root": "grub",
        "meaning": "A larva of an insect, or something that digs in the ground",
        "language": "Middle English"
      }
    ],
    "historicalDevelopment": "源自中古英语 'grobbe'，最初指短粗的人或昆虫幼虫，17世纪开始扩展到表示肮脏或低劣的状态，19世纪时在英语中广泛用于描述外表不洁净的事物。",
    "firstKnownUse": "17th century",
    "relatedWords": [
      "grub",
      "grubbiness"
    ]
  },
  "difficultyAnalysis": {
    "overallLevel": "B1",
    "pronunciationDifficulty": "4",
    "spellingDifficulty": "3",
    "meaningComplexity": "5",
    "usageComplexity": "4",
    "learningTips": [
      "结合认知科学，利用视觉联想将 'grubby' 与泥土或脏手等形象联系起来，以加强记忆；建议初级学习者通过重复上下文练习，避免混淆与类似词汇的语义差异。"
    ]
  },
  "semanticRelations": {
    "synonyms": [
      {
        "word": "dirty",
        "similarity": "0.8",
        "context": "适用于日常描述，如 'dirty clothes' 表示衣服肮脏，与 'grubby' 在非正式语境中可互换"
      },
      {
        "word": "filthy",
        "similarity": "0.7",
        "context": "适用于更强烈的肮脏描述，如 'filthy room'，在非正式或情感化语境中使用"
      }
    ],
    "antonyms": [
      {
        "word": "clean",
        "context": "适用于对比语境，如 'clean hands' 与 'grubby hands'，强调整洁与肮脏的差异"
      },
      {
        "word": "neat",
        "context": "在正式描述外表时使用，如 'neat appearance' 表示整洁，与 'grubby' 在个人卫生语境中对立"
      }
    ],
    "hypernyms": [
      "dirty"
    ],
    "hyponyms": [
      "muddy",
      "stained"
    ],
    "collocations": [
      {
        "pattern": "Adjective + Noun (e.g., grubby + hands/clothes)",
        "examples": [
          "grubby fingers",
          "grubby jacket"
        ],
        "strength": "strong"
      },
      {
        "pattern": "Adverb + Adjective (e.g., very grubby)",
        "examples": [
          "extremely grubby room"
        ],
        "strength": "medium"
      }
    ]
  },
  "culturalContext": {
    "culturalSignificance": "该词在英语文化中象征个人卫生和社会阶层的隐含语义，常用于文学或媒体中描述贫困或忽视，常反映出对整洁的西方文化价值观。",
    "regionalVariations": [
      {
        "region": "英国",
        "variation": "更常用于非正式口语中，强调日常生活的肮脏感",
        "usage": "在英国英语中，可能与阶级相关，如在乡村或工人阶级语境中使用"
      },
      {
        "region": "美国",
        "variation": "类似使用，但可能更中性化，不带强烈阶级色彩",
        "usage": "在美国英语中，常在儿童故事或家庭场景中出现"
      }
    ],
    "historicalContext": "与工业革命时期的英国社会背景相关，常描述工人阶级的肮脏生活，在维多利亚时代文学如狄更斯作品中出现。",
    "modernUsage": "在现代社交媒体如Twitter或Instagram上，用于幽默或自嘲描述日常生活的凌乱趋势。"
  },
  "memoryAids": {
    "visualScene": {
      "description": "想象一个孩子在花园里玩耍后，手上满是泥土和灰尘，呈现出肮脏的样子。",
      "keyElements": [
        "泥土",
        "灰尘",
        "孩子的手"
      ],
      "emotionalConnection": "联结到个人童年玩耍的回忆，触发幽默或怀旧情绪以加深记忆"
    },
    "mnemonicDevices": [
      {
        "type": "联想",
        "content": "将 'grubby' 联想成 'grub' (虫子) + 'y' (表示特征)，想象虫子爬过的表面变得脏乱。",
        "explanation": "通过视觉联想强化词汇记忆，利用认知科学中的双编码理论，将图像与声音结合"
      },
      {
        "type": "声音联觉",
        "content": "发音 '/ɡrʌbi/' 听起来像 'grabby' (抓取的)，联想为抓取泥土的手变得肮脏。",
        "explanation": "利用声音相似性创建记忆路径，基于认知心理学中的关联学习"
      }
    ],
    "wordAssociations": [
      "dirty",
      "muddy",
      "scruffy"
    ]
  },
  "grammaticalInfo": {
    "irregularForms": {
      "plural": null,
      "pastTense": null,
      "pastParticiple": null,
      "presentParticiple": null,
      "comparative": "grubbier",
      "superlative": "grubbiest"
    },
    "syntacticPatterns": [
      {
        "pattern": "Adjective + Noun",
        "description": "用作定语修饰名词，描述名词的肮脏状态",
        "examples": [
          "grubby shirt"
        ]
      },
      {
        "pattern": "Be + Adjective",
        "description": "用在系动词后描述主语的状态",
        "examples": [
          "The room is grubby."
        ]
      }
    ],
    "commonMistakes": [
      {
        "mistake": "Confusing with 'grabby' (meaning eager to grab)",
        "correction": "Use 'grubby' for dirtiness and 'grabby' for greediness",
        "explanation": "语义混淆可能因发音相似，学习者需注意上下文区分"
      },
      {
        "mistake": "Overusing in formal writing",
        "correction": "Replace with 'dirty' or 'soiled' in formal contexts",
        "explanation": "该词为非正式语域，避免在正式文章中使用"
      }
    ]
  },
  "metadata": {
    "frequency": "Medium (e.g., ranked around 5000 in COCA corpus)",
    "domains": [
      "日常语言",
      "文学",
      "儿童教育"
    ],
    "tags": [
      "形容词",
      "卫生相关",
      "非正式"
    ],
    "lastUpdated": "2023-10",
    "sources": [
      "Oxford English Dictionary (OED)",
      "Corpus of Contemporary American English (COCA)",
      "British National Corpus (BNC)"
    ]
  }
}