{
  "word": "hybridise",
  "phonetics": {
    "british": "/ˈhaɪbrɪdaɪz/",
    "american": "/ˈhaɪbrəˌdaɪz/"
  },
  "definitions": [
    {
      "partOfSpeech": "verb",
      "definition": "to produce or cause to produce hybrids, especially by cross-breeding plants, animals, or other organisms",
      "chineseTranslation": "使杂交；混合",
      "level": "intermediate",
      "frequency": "medium",
      "register": "neutral"
    },
    {
      "partOfSpeech": "verb",
      "definition": "to combine or merge different elements, such as ideas, technologies, or cultures, to form something new",
      "chineseTranslation": "使混合；融合",
      "level": "intermediate",
      "frequency": "medium",
      "register": "formal"
    }
  ],
  "phrases": [
    {
      "phrase": "hybridise plants",
      "meaning": "使植物杂交",
      "example": "Botanists often hybridise plants to develop disease-resistant varieties.",
      "exampleTranslation": "植物学家经常使植物杂交以开发抗病品种。",
      "frequency": "medium"
    },
    {
      "phrase": "hybridise genes",
      "meaning": "使基因杂交",
      "example": "Genetic engineers hybridise genes from different species to create enhanced organisms.",
      "exampleTranslation": "遗传工程师使不同物种的基因杂交以创建增强型生物。",
      "frequency": "low"
    },
    {
      "phrase": "hybridise cultures",
      "meaning": "使文化融合",
      "example": "Globalization has led societies to hybridise cultures through exchange and adaptation.",
      "exampleTranslation": "全球化导致社会通过交流和适应使文化融合。",
      "frequency": "medium"
    }
  ],
  "examples": [
    {
      "sentence": "In agriculture, farmers hybridise crops to improve yield and resilience.",
      "translation": "在农业中，农民使农作物杂交以提高产量和韧性。",
      "source": "Scientific literature (e.g., academic journals)",
      "difficulty": "intermediate"
    },
    {
      "sentence": "The artist decided to hybridise traditional painting techniques with digital media.",
      "translation": "这位艺术家决定将传统绘画技巧与数字媒体融合。",
      "source": "Art and culture discussions",
      "difficulty": "intermediate"
    },
    {
      "sentence": "Scientists are working to hybridise electric and internal combustion engines for eco-friendly vehicles.",
      "translation": "科学家们正在努力使电动和内燃机杂交以生产环保车辆。",
      "source": "News articles (e.g., BBC News)",
      "difficulty": "advanced"
    }
  ],
  "etymology": {
    "origin": "Latin",
    "rootWords": [
      {
        "root": "hybrida",
        "meaning": "mongrel or mixed breed",
        "language": "Latin"
      }
    ],
    "historicalDevelopment": "源自拉丁语 'hybrida'，意为杂种或混血动物。词语在17世纪传入英语，最初用于生物学领域描述物种杂交。随着科学进步，该词扩展到更广泛的混合概念，如文化和技术融合。",
    "firstKnownUse": "1605",
    "relatedWords": [
      "hybrid",
      "hybridization",
      "hybride"
    ]
  },
  "difficultyAnalysis": {
    "overallLevel": "B2",
    "pronunciationDifficulty": "6",
    "spellingDifficulty": "7",
    "meaningComplexity": "5",
    "usageComplexity": "6",
    "learningTips": [
      "利用认知科学中的双编码理论，将词汇与视觉图像结合，例如想象两种植物交织生长的场景，以增强记忆；通过重复练习在上下文中使用词汇，避免孤立学习。"
    ]
  },
  "semanticRelations": {
    "synonyms": [
      {
        "word": "crossbreed",
        "similarity": "0.8",
        "context": "在生物学或农业语境中，尤指物种杂交"
      },
      {
        "word": "interbreed",
        "similarity": "0.7",
        "context": "适用于动物或植物的遗传混合语境"
      }
    ],
    "antonyms": [
      {
        "word": "purebreed",
        "context": "在强调纯净血统或未混合的语境中"
      },
      {
        "word": "segregate",
        "context": "在分离或隔离不同元素的文化或科学语境中"
      }
    ],
    "hypernyms": [
      "breed",
      "mix"
    ],
    "hyponyms": [
      "genetically modify",
      "cross-pollinate"
    ],
    "collocations": [
      {
        "pattern": "hybridise with",
        "examples": [
          "hybridise with another species"
        ],
        "strength": "strong"
      },
      {
        "pattern": "hybridise to",
        "examples": [
          "hybridise to create new varieties"
        ],
        "strength": "medium"
      }
    ]
  },
  "culturalContext": {
    "culturalSignificance": "该词在现代文化中象征创新和多样性，例如在环保运动中代表可持续发展的混合技术；在西方文化中，与达尔文进化论相关，隐含物种适应的隐喻。",
    "regionalVariations": [
      {
        "region": "美国",
        "variation": "hybridize",
        "usage": "美国英语中常用 'hybridize' 作为标准拼写形式，而英国英语保留 'hybridise'，反映了英式和美式拼写差异。"
      },
      {
        "region": "英国",
        "variation": "hybridise",
        "usage": "在正式学术语境中更常见，强调历史传承。"
      }
    ],
    "historicalContext": "与19世纪的生物学革命相关，如达尔文的《物种起源》，该词体现了工业革命后科学与文化融合的趋势。",
    "modernUsage": "在社交媒体和科技领域流行，例如讨论混合能源汽车或文化融合，常用于表达全球化的积极方面。"
  },
  "memoryAids": {
    "visualScene": {
      "description": "想象一棵树与另一棵树交织生长，产生一种新型果实。",
      "keyElements": [
        "树木",
        "交织",
        "新果实"
      ],
      "emotionalConnection": "联结到个人创新经历，如尝试新食谱，触发成就感。"
    },
    "mnemonicDevices": [
      {
        "type": "联想",
        "content": "将 'hybridise' 联想为 'hybrid car'（混合动力汽车），代表混合概念。",
        "explanation": "通过声音和图像联想，增强词汇在脑中的视觉表示，提高长期记忆。"
      },
      {
        "type": "缩略",
        "content": "H-Y-BRID-ise = Hybrid You Build Rapidly In Diversity",
        "explanation": "创建缩略词以分解词汇结构，利用重复强化记忆路径。"
      }
    ],
    "wordAssociations": [
      "mix",
      "blend",
      "fuse",
      "cross"
    ]
  },
  "grammaticalInfo": {
    "irregularForms": {
      "plural": null,
      "pastTense": "hybridised",
      "pastParticiple": "hybridised",
      "presentParticiple": "hybridising",
      "comparative": null,
      "superlative": null
    },
    "syntacticPatterns": [
      {
        "pattern": "Subject + hybridise + object",
        "description": "主语 + 动词 + 宾语结构，常用于描述动作过程",
        "examples": [
          "Researchers hybridise species in the lab."
        ]
      },
      {
        "pattern": "hybridise + to-infinitive",
        "description": "后接不定式，表示目的",
        "examples": [
          "They hybridise plants to increase resistance."
        ]
      }
    ],
    "commonMistakes": [
      {
        "mistake": "Confusing 'hybridise' with 'hybridize'",
        "correction": "Use 'hybridise' in British English contexts",
        "explanation": "由于英美拼写差异，学习者可能混淆；建议根据语境选择正确形式。"
      },
      {
        "mistake": "Incorrectly using as a noun",
        "correction": "Use as a verb only; for noun form, use 'hybridisation'",
        "explanation": "该词主要是动词，避免误用为名词以符合语法规则。"
      }
    ]
  },
  "metadata": {
    "frequency": "Medium (ranked around 15,000 in COCA corpus)",
    "domains": [
      "Science",
      "Biology",
      "Technology",
      "Culture"
    ],
    "tags": [
      "Genetics",
      "Innovation",
      "Fusion"
    ],
    "lastUpdated": "2023-10",
    "sources": [
      "OED (Oxford English Dictionary)",
      "COCA (Corpus of Contemporary American English)",
      "BNC (British National Corpus)"
    ]
  }
}