{
  "word": "nocuous",
  "phonetics": {
    "british": "/ˈnɒk.ju.əs/",
    "american": "/ˈnɑː.kju.əs/"
  },
  "definitions": [
    {
      "partOfSpeech": "adjective",
      "definition": "Harmful or injurious to health, well-being, or the environment.",
      "chineseTranslation": "有害的",
      "level": "advanced",
      "frequency": "low",
      "register": "formal"
    }
  ],
  "phrases": [
    {
      "phrase": "nocuous effects",
      "meaning": "有害的影响",
      "example": "The nocuous effects of prolonged exposure to radiation were documented in the study.",
      "exampleTranslation": "研究中记录了长时间暴露于辐射的有害影响。",
      "frequency": "low"
    },
    {
      "phrase": "nocuous substances",
      "meaning": "有害物质",
      "example": "Factories must handle nocuous substances with extreme care to prevent environmental damage.",
      "exampleTranslation": "工厂必须极其小心地处理有害物质，以防止环境破坏。",
      "frequency": "low"
    }
  ],
  "examples": [
    {
      "sentence": "The scientist warned about the nocuous properties of the new chemical compound.",
      "translation": "科学家警告了这种新化学化合物的有害特性。",
      "source": "Scientific literature (e.g., academic journals)",
      "difficulty": "advanced"
    },
    {
      "sentence": "In urban areas, nocuous air pollution can lead to respiratory diseases among residents.",
      "translation": "在城市地区，有害的空气污染可能导致居民患上呼吸道疾病。",
      "source": "Environmental reports",
      "difficulty": "intermediate"
    },
    {
      "sentence": "Despite its benefits, the pesticide has nocuous side effects on beneficial insects.",
      "translation": "尽管有好处，这种杀虫剂对有益昆虫有有害的副作用。",
      "source": "News articles",
      "difficulty": "advanced"
    }
  ],
  "etymology": {
    "origin": "Latin",
    "rootWords": [
      {
        "root": "nocuus",
        "meaning": "harmful or hurtful",
        "language": "Latin"
      }
    ],
    "historicalDevelopment": "源自拉丁语 'nocuus'，意为伤害性的，该词源自 'nocere'（伤害）。在英语中，它作为形容词演变，但使用非常罕见，可能受拉丁语影响通过法语传入17世纪的英语。",
    "firstKnownUse": "17th century",
    "relatedWords": [
      "noxious",
      "innocuous"
    ]
  },
  "difficultyAnalysis": {
    "overallLevel": "C1",
    "pronunciationDifficulty": 7,
    "spellingDifficulty": 8,
    "meaningComplexity": 6,
    "usageComplexity": 7,
    "learningTips": [
      "结合认知科学，将该词与类似词汇如'noxious'进行声音联想，以增强记忆痕迹；",
      "使用间隔重复法在正式语境中练习，避免混淆反义词；",
      "通过视觉化方法，将'nocuous'与有害场景关联，以强化语义网络"
    ]
  },
  "semanticRelations": {
    "synonyms": [
      {
        "word": "harmful",
        "similarity": 0.9,
        "context": "在描述负面健康或环境影响时"
      },
      {
        "word": "injurious",
        "similarity": 0.8,
        "context": "在法律或医疗语境中描述损害"
      },
      {
        "word": "detrimental",
        "similarity": 0.7,
        "context": "在正式讨论中强调不利后果"
      }
    ],
    "antonyms": [
      {
        "word": "innocuous",
        "context": "在描述无害或安全的事物时"
      },
      {
        "word": "harmless",
        "context": "在日常或非正式语境中对比风险"
      }
    ],
    "hypernyms": [
      "harmful"
    ],
    "hyponyms": [
      "toxic",
      "poisonous"
    ],
    "collocations": [
      {
        "pattern": "nocuous + noun (e.g., substances, effects)",
        "examples": [
          "nocuous gases",
          "nocuous impacts"
        ],
        "strength": "weak"
      },
      {
        "pattern": "be + nocuous",
        "examples": [
          "The radiation is nocuous."
        ],
        "strength": "medium"
      }
    ]
  },
  "culturalContext": {
    "culturalSignificance": "该词在英语文化中象征潜在风险或危害，常用于科学和技术语境，隐含语义强调预防和责任，但在现代社会中较少使用，更多被'noxious'取代。",
    "regionalVariations": [
      {
        "region": "United Kingdom",
        "variation": "使用频率较低，主要在学术写作中",
        "usage": "在英国英语中，偏好正式语境，如环境政策讨论"
      },
      {
        "region": "United States",
        "variation": "与英国类似，但更倾向于科学报告",
        "usage": "在美国英语中，常见于环境法规或健康警示"
      }
    ],
    "historicalContext": "与工业革命相关的环境和健康问题有关，在17世纪传入英语后，主要在文学和科学作品中出现，例如启蒙运动时期的著作讨论有害物质。",
    "modernUsage": "在现代社交媒体和数字语境中，该词很少出现，更多在专业论坛或学术论文中传播，反映出对环境可持续性的关注。"
  },
  "memoryAids": {
    "visualScene": {
      "description": "想象一个警示标志上的瓶子，里面是冒烟的液体，标签写着'nocuous'，代表危险。",
      "keyElements": [
        "警示标志",
        "冒烟液体",
        "危险标签"
      ],
      "emotionalConnection": "联结到个人经历，如曾经接触过有害化学品的情绪，以增强情感记忆"
    },
    "mnemonicDevices": [
      {
        "type": "联想",
        "content": "Nocuous 听起来像 'noxious'，两者都表示有害。",
        "explanation": "通过声音相似性建立认知联想，强化词汇在脑中的位置"
      },
      {
        "type": "缩略",
        "content": "N-O-C = Not Only Harmful, But Cautious.",
        "explanation": "使用缩写形式创建简易记忆钩子，结合视觉想象以提高保留率"
      }
    ],
    "wordAssociations": [
      "noxious",
      "toxic",
      "dangerous",
      "hazardous"
    ]
  },
  "grammaticalInfo": {
    "irregularForms": {
      "plural": null,
      "pastTense": null,
      "pastParticiple": null,
      "presentParticiple": null,
      "comparative": "more nocuous",
      "superlative": "most nocuous"
    },
    "syntacticPatterns": [
      {
        "pattern": "Subject + be + nocuous",
        "description": "用于描述主语具有有害性质",
        "examples": [
          "The chemical is nocuous."
        ]
      },
      {
        "pattern": "nocuous + noun phrase",
        "description": "在句子中修饰名词，表示负面影响",
        "examples": [
          "The nocuous effects were analyzed."
        ]
      }
    ],
    "commonMistakes": [
      {
        "mistake": "Confusing 'nocuous' with 'innocuous'",
        "correction": "Use 'nocuous' for harmful meanings",
        "explanation": "它们是反义词，常因拼写相似导致错误"
      },
      {
        "mistake": "Overusing in informal contexts",
        "correction": "Restrict to formal or technical writing",
        "explanation": "该词语域为正式，避免在口语中使用以防止不适"
      }
    ]
  },
  "metadata": {
    "frequency": "Very low (e.g., not in top 100,000 in COCA corpus)",
    "domains": [
      "Science",
      "Medicine",
      "Environment"
    ],
    "tags": [
      "adjective",
      "harmful",
      "rare"
    ],
    "lastUpdated": "2023-10",
    "sources": [
      "OED (Oxford English Dictionary)",
      "Merriam-Webster",
      "COCA (Corpus of Contemporary American English)"
    ]
  }
}