{
  "word": "pentarchy",
  "phonetics": {
    "british": "/ˈpɛntɑːki/",
    "american": "/ˈpɛntɑrki/"
  },
  "definitions": [
    {
      "partOfSpeech": "noun",
      "definition": "A system of government by five joint rulers or a confederacy consisting of five states or territories.",
      "chineseTranslation": "五人联合统治或五国联邦",
      "level": "advanced",
      "frequency": "low",
      "register": "formal"
    }
  ],
  "phrases": [
    {
      "phrase": "the Pentarchy",
      "meaning": "早期基督教的五位主教辖区",
      "example": "The Pentarchy refers to the five great sees of the early Christian Church.",
      "exampleTranslation": "Pentarchy 指的是早期基督教的五个主要主教辖区。",
      "frequency": "low"
    },
    {
      "phrase": "Byzantine Pentarchy",
      "meaning": "拜占庭帝国的五重统治结构",
      "example": "The Byzantine Pentarchy was a key element in the ecclesiastical organization of the Eastern Roman Empire.",
      "exampleTranslation": "拜占庭 Pentarchy 是东罗马帝国教会组织中的关键元素。",
      "frequency": "low"
    }
  ],
  "examples": [
    {
      "sentence": "The concept of pentarchy emerged in the context of ancient Greek city-states.",
      "translation": "五重统治的概念出现在古希腊城邦的背景下。",
      "source": "Historical texts, such as those from Byzantine studies",
      "difficulty": "advanced"
    },
    {
      "sentence": "In modern political theory, pentarchy is rarely discussed outside academic circles.",
      "translation": "在现代政治理论中，五重统治很少在学术圈外被讨论。",
      "source": "Academic publications, e.g., journals on political history",
      "difficulty": "advanced"
    },
    {
      "sentence": "Scholars debate whether the pentarchy truly functioned as a balanced system of governance.",
      "translation": "学者们争论五重统治是否真正作为一个平衡的治理系统运作。",
      "source": "News articles and books on ecclesiastical history",
      "difficulty": "intermediate"
    }
  ],
  "etymology": {
    "origin": "希腊语",
    "rootWords": [
      {
        "root": "penta-",
        "meaning": "五",
        "language": "希腊语"
      },
      {
        "root": "archy",
        "meaning": "统治",
        "language": "希腊语"
      }
    ],
    "historicalDevelopment": "该词源自希腊语 'pente'（五）和 'arkhein'（统治），最初用于描述古希腊或罗马时期的多重统治形式。19世纪时，在历史和神学语境中演变为现代含义，尤其与拜占庭帝国的教会结构相关。从词源到现代，该词的含义从泛指五重统治扩展到特定历史语境，如基督教的五位牧首。",
    "firstKnownUse": "约1844年",
    "relatedWords": [
      "monarchy",
      "oligarchy",
      "hierarchy"
    ]
  },
  "difficultyAnalysis": {
    "overallLevel": "C1",
    "pronunciationDifficulty": "5",
    "spellingDifficulty": "6",
    "meaningComplexity": "7",
    "usageComplexity": "8",
    "learningTips": [
      "结合认知科学原理，使用视觉联想将 'pent-' 与五边形（pentagon）关联，以强化记忆；通过重复暴露于历史语境中增强语义理解；建议使用间隔重复法（spaced repetition）来处理抽象概念。"
    ]
  },
  "semanticRelations": {
    "synonyms": [
      {
        "word": "oligarchy",
        "similarity": "0.6",
        "context": "适用于描述多重统治的正式语境中"
      },
      {
        "word": "pentapolis",
        "similarity": "0.4",
        "context": "在历史或地理语境中，指五个城市的联盟"
      }
    ],
    "antonyms": [
      {
        "word": "monarchy",
        "context": "在对比单一统治与多重统治的语境中"
      }
    ],
    "hypernyms": [
      "government system"
    ],
    "hyponyms": [
      "Byzantine Pentarchy"
    ],
    "collocations": [
      {
        "pattern": "Noun + Pentarchy",
        "examples": [
          "the Byzantine Pentarchy"
        ],
        "strength": "strong"
      },
      {
        "pattern": "Pentarchy as a form of",
        "examples": [
          "pentarchy as a form of governance"
        ],
        "strength": "medium"
      }
    ]
  },
  "culturalContext": {
    "culturalSignificance": "该词在基督教和拜占庭文化中象征着权力分散和教会组织的平衡，常隐含平等与合作的语义；在跨文化语境中，它反映了西方历史学对多中心治理的解读。",
    "regionalVariations": [
      {
        "region": "英国",
        "variation": "更侧重于历史和神学语境",
        "usage": "在英国学术界，常用于讨论东正教历史"
      },
      {
        "region": "美国",
        "variation": "偶尔用于政治理论讨论",
        "usage": "在美国，更可能出现在大学课程或专业出版物中"
      }
    ],
    "historicalContext": "与拜占庭帝国和早期基督教的五位牧首（罗马、君士坦丁堡、亚历山大港、安条克、耶路撒冷）相关，体现了中世纪欧洲权力结构的文化和社会背景。",
    "modernUsage": "在现代社交媒体和学术讨论中，该词的使用趋势较低，主要出现在历史频道或在线教育平台上，体现了对古典治理模式的反思。"
  },
  "memoryAids": {
    "visualScene": {
      "description": "想象五个王冠戴在五个王座上的场景，每个王座代表一个统治者。",
      "keyElements": [
        "五个王座",
        "王冠",
        "平衡结构"
      ],
      "emotionalConnection": "联结到个人经验，如团队合作的情绪，以强化记忆的持久性"
    },
    "mnemonicDevices": [
      {
        "type": "联想",
        "content": "Pentarchy 像 pentagon（五边形）加上archy（统治），所以是五个统治者的形状。",
        "explanation": "通过视觉联想帮助记忆词根，基于认知科学的空间记忆原理"
      },
      {
        "type": "缩略",
        "content": "P-E-N-T-A-R-C-H-Y: Five Equals Need To Act as Rulers, Creating Harmony and Yield.",
        "explanation": "使用首字母缩略法结合故事元素，促进情感和语义记忆"
      }
    ],
    "wordAssociations": [
      "pentagon",
      "monarchy",
      "hierarchy"
    ]
  },
  "grammaticalInfo": {
    "irregularForms": {
      "plural": "pentarchies",
      "pastTense": null,
      "pastParticiple": null,
      "presentParticiple": null,
      "comparative": null,
      "superlative": null
    },
    "syntacticPatterns": [
      {
        "pattern": "Subject + Verb + Pentarchy",
        "description": "作为主语的典型结构，用于描述概念",
        "examples": [
          "Pentarchy influenced ancient governance."
        ]
      },
      {
        "pattern": "Adjective + Pentarchy",
        "description": "用形容词修饰的结构，强调特征",
        "examples": [
          "The Byzantine Pentarchy was complex."
        ]
      }
    ],
    "commonMistakes": [
      {
        "mistake": "Confusing with 'pentagon'",
        "correction": "Use 'pentarchy' only for governance contexts",
        "explanation": "由于词根相似，学习者可能混淆；建议通过语境区分"
      },
      {
        "mistake": "Incorrect pluralization",
        "correction": "pentarchies",
        "explanation": "英语名词规则需注意，添加 -ies 于以 -y 结尾的词"
      }
    ]
  },
  "metadata": {
    "frequency": "Low (e.g., ranked below 50,000 in COCA corpus)",
    "domains": [
      "历史",
      "政治",
      "宗教"
    ],
    "tags": [
      "治理",
      "历史术语",
      "基督教"
    ],
    "lastUpdated": "2023-10",
    "sources": [
      "OED (Oxford English Dictionary)",
      "COCA (Corpus of Contemporary American English)",
      "Etymonline"
    ]
  }
}