{
  "word": "recommended",
  "phonetics": {
    "british": "/ˌrɛkəˈmɛndɪd/",
    "american": "/ˌrɛkəˈmɛndɪd/"
  },
  "definitions": [
    {
      "partOfSpeech": "adjective",
      "definition": "Suggested or put forward as being good, suitable, or advisable for a particular purpose.",
      "chineseTranslation": "推荐的",
      "level": "intermediate",
      "frequency": "high",
      "register": "neutral"
    },
    {
      "partOfSpeech": "verb (past participle of recommend)",
      "definition": "Having been suggested or advised as a course of action.",
      "chineseTranslation": "被推荐的",
      "level": "intermediate",
      "frequency": "high",
      "register": "neutral"
    }
  ],
  "phrases": [
    {
      "phrase": "highly recommended",
      "meaning": "强烈推荐的",
      "example": "This restaurant is highly recommended by food critics.",
      "exampleTranslation": "这家餐厅被美食评论家强烈推荐。",
      "frequency": "high"
    },
    {
      "phrase": "not recommended",
      "meaning": "不推荐的",
      "example": "Swimming in that lake is not recommended due to pollution.",
      "exampleTranslation": "由于污染，不推荐在那湖里游泳。",
      "frequency": "medium"
    },
    {
      "phrase": "recommended daily allowance",
      "meaning": "推荐每日摄入量",
      "example": "The recommended daily allowance of vitamin C is 75 mg for adults.",
      "exampleTranslation": "成人每天推荐摄入维生素C的量是75毫克。",
      "frequency": "medium"
    }
  ],
  "examples": [
    {
      "sentence": "The doctor recommended a low-sodium diet for better heart health.",
      "translation": "医生推荐低钠饮食以改善心脏健康。",
      "source": "Health and medical literature (e.g., from WHO guidelines)",
      "difficulty": "intermediate"
    },
    {
      "sentence": "This book is recommended for anyone interested in modern history.",
      "translation": "这本书推荐给任何对现代历史感兴趣的人。",
      "source": "Book reviews (e.g., from The New York Times)",
      "difficulty": "intermediate"
    },
    {
      "sentence": "Experts recommended investing in renewable energy to combat climate change.",
      "translation": "专家推荐投资可再生能源以应对气候变化。",
      "source": "News articles (e.g., from BBC News)",
      "difficulty": "intermediate"
    }
  ],
  "etymology": {
    "origin": "Latin",
    "rootWords": [
      {
        "root": "recommendare",
        "meaning": "to commend or entrust",
        "language": "Latin"
      }
    ],
    "historicalDevelopment": "源自拉丁语 'recommendare'，由 're-'（再次）和 'commendare'（委托或赞扬）组成。该词在中世纪拉丁语中演变为 'recommend'，意思是建议或介绍。进入英语后，从14世纪开始用于表示正式建议，现代英语中强调积极推荐。",
    "firstKnownUse": "14th century",
    "relatedWords": [
      "recommend",
      "commend",
      "mandate"
    ]
  },
  "difficultyAnalysis": {
    "overallLevel": "B2 (CEFR)",
    "pronunciationDifficulty": "4 (out of 10, as the word involves common vowel sounds but requires attention to stress on the third syllable)",
    "spellingDifficulty": "3 (out of 10, straightforward with common letter patterns, but double 'm' and 'e' may confuse intermediate learners)",
    "meaningComplexity": "5 (out of 10, meanings are context-dependent but not overly abstract for intermediate learners)",
    "usageComplexity": "4 (out of 10, often used in advice-giving contexts, but requires understanding of modifiers like 'highly')",
    "learningTips": [
      "结合认知科学原理，使用分块记忆法，将 'recommended' 与实际生活建议场景关联，如医生咨询；通过重复曝光于真实语料库中提升记忆持久性；建议初级学习者创建个人联想网，将其与中文 '推荐' 的情境连接，以强化双语迁移。"
    ]
  },
  "semanticRelations": {
    "synonyms": [
      {
        "word": "suggested",
        "similarity": "0.8",
        "context": "适用于非正式建议语境，如日常对话中"
      },
      {
        "word": "advised",
        "similarity": "0.7",
        "context": "适用于专业或正式场合，如医疗建议"
      }
    ],
    "antonyms": [
      {
        "word": "discouraged",
        "context": "适用于不推荐的语境，例如 'This activity is discouraged for safety reasons.'（出于安全原因，不推荐此活动。）"
      },
      {
        "word": "advised against",
        "context": "适用于强烈反对的语境，例如商业决策中"
      }
    ],
    "hypernyms": [
      "suggested"
    ],
    "hyponyms": [
      "highly recommended",
      "strongly advised"
    ],
    "collocations": [
      {
        "pattern": "Verb + recommended (e.g., is recommended, was recommended)",
        "examples": [
          "This method is recommended for beginners."
        ],
        "strength": "strong"
      },
      {
        "pattern": "Adverb + recommended (e.g., highly recommended)",
        "examples": [
          "It is highly recommended to book in advance."
        ],
        "strength": "medium"
      }
    ]
  },
  "culturalContext": {
    "culturalSignificance": "在英语文化中，该词象征信任和专家意见，常用于消费主义社会，如产品评论或旅游建议，隐含语义强调基于经验的指导。",
    "regionalVariations": [
      {
        "region": "美国",
        "variation": "更常用在非正式语境，如在线评论",
        "usage": "在美国英语中，常见于电商平台，如 'Amazon recommended products'（亚马逊推荐产品），强调个性化推荐。"
      },
      {
        "region": "英国",
        "variation": "略微正式化，常用于学术或官方建议",
        "usage": "在英国英语中，可能在政府报告中出现，如 'The committee recommended reforms.'（委员会推荐改革。），反映集体决策文化。"
      }
    ],
    "historicalContext": "该词与启蒙运动相关的理性主义文化关联，强调基于证据的建议；在文学中，如莎士比亚作品中，类似词汇用于人物忠告。",
    "modernUsage": "在现代社交媒体和数字平台上，该词流行于用户生成内容，如YouTube推荐视频，反映全球化消费趋势。"
  },
  "memoryAids": {
    "visualScene": {
      "description": "想象一个朋友拿着一个书籍列表，指着其中一本说 'This is recommended!'，场景中包括书本和对话泡泡。",
      "keyElements": [
        "书籍",
        "朋友建议",
        "对话泡泡"
      ],
      "emotionalConnection": "联结个人经验，如回想自己接受朋友推荐的经历，以触发积极情绪和记忆巩固。"
    },
    "mnemonicDevices": [
      {
        "type": "联想",
        "content": "将 'recommended' 联想为 're-commend-ed'，想象 're' 如重复，'commend' 如赞扬朋友。",
        "explanation": "通过视觉联想强化词根记忆，基于认知科学的空间记忆原理。"
      },
      {
        "type": "声音联觉",
        "content": "发音 /ˌrɛkəˈmɛndɪd/ 联想到 'reckon a mend'，意思是 '计算一个修复'，象征建议修复问题。",
        "explanation": "利用声音相似性创建双重编码，提升记忆保留率。"
      }
    ],
    "wordAssociations": [
      "suggest",
      "advise",
      "endorse"
    ]
  },
  "grammaticalInfo": {
    "irregularForms": {
      "plural": null,
      "pastTense": null,
      "pastParticiple": null,
      "presentParticiple": null,
      "comparative": "more recommended (though less common)",
      "superlative": "most recommended"
    },
    "syntacticPatterns": [
      {
        "pattern": "Subject + be + recommended + for + object",
        "description": "主语 + be 动词 + recommended + for + 宾语，常用于建议结构",
        "examples": [
          "This app is recommended for learning languages."
        ]
      },
      {
        "pattern": "Verb + recommended + object",
        "description": "动词 + recommended + 宾语，用于过去分词结构",
        "examples": [
          "The guide recommended the hotel."
        ]
      }
    ],
    "commonMistakes": [
      {
        "mistake": "Using 'recommend' instead of 'recommended' in adjective contexts",
        "correction": "Use 'recommended' as adjective",
        "explanation": "学习者常混淆动词和形容词形式，导致句法错误；正确使用需注意语境。"
      },
      {
        "mistake": "Overusing in informal speech",
        "correction": "Balance with synonyms in formal writing",
        "explanation": "中级学习者可能在正式语域中过度使用，建议通过语料库练习区分语域。"
      }
    ]
  },
  "metadata": {
    "frequency": "High (ranked in top 2000 words in COCA corpus, with approximately 500 occurrences per million words)",
    "domains": [
      "education",
      "health",
      "commerce",
      "media"
    ],
    "tags": [
      "advice",
      "suggestion",
      "recommendation"
    ],
    "lastUpdated": "2023-10",
    "sources": [
      "OED (Oxford English Dictionary)",
      "COCA (Corpus of Contemporary American English)",
      "BNC (British National Corpus)"
    ]
  }
}