{
  "word": "verdant",
  "phonetics": {
    "british": "/ˈvɜː.dənt/",
    "american": "/ˈvɝ.dənt/"
  },
  "definitions": [
    {
      "partOfSpeech": "adjective",
      "definition": "green with grass or other vegetation; lush and verdant in appearance",
      "chineseTranslation": "绿油油的；青翠的",
      "level": "intermediate",
      "frequency": "medium",
      "register": "neutral"
    },
    {
      "partOfSpeech": "adjective",
      "definition": "inexperienced or naive, often used figuratively",
      "chineseTranslation": "缺乏经验的；天真的",
      "level": "advanced",
      "frequency": "low",
      "register": "formal"
    }
  ],
  "phrases": [
    {
      "phrase": "verdant fields",
      "meaning": "绿油油的田野",
      "example": "The verdant fields of the countryside attract many hikers.",
      "exampleTranslation": "乡村的绿油油田野吸引了许多徒步旅行者。",
      "frequency": "medium"
    },
    {
      "phrase": "verdant landscape",
      "meaning": "青翠的景观",
      "example": "Artists often paint the verdant landscape of the national park.",
      "exampleTranslation": "艺术家们经常描绘国家公园的青翠景观。",
      "frequency": "medium"
    }
  ],
  "examples": [
    {
      "sentence": "After the spring rains, the hills became verdant and full of life.",
      "translation": "春雨过后，山丘变得绿油油的，生机勃勃。",
      "source": "Literature (e.g., nature poetry)",
      "difficulty": "intermediate"
    },
    {
      "sentence": "The verdant valleys of Ireland are a testament to its rich agricultural history.",
      "translation": "爱尔兰的青翠山谷见证了其丰富的农业历史。",
      "source": "Travel writing",
      "difficulty": "intermediate"
    },
    {
      "sentence": "In a metaphorical sense, the young intern was still verdant in the ways of corporate politics.",
      "translation": "从比喻意义上讲，这位年轻实习生在公司政治方面仍很天真。",
      "source": "Modern fiction",
      "difficulty": "advanced"
    }
  ],
  "etymology": {
    "origin": "Latin",
    "rootWords": [
      {
        "root": "viridis",
        "meaning": "green",
        "language": "Latin"
      }
    ],
    "historicalDevelopment": "源自拉丁语 'viridis'，意为绿色，通过古法语 'vert' 演变为中古英语 'vertant'，最终在16世纪早期发展为现代英语 'verdant'，最初用于描述植物的茂盛，逐渐扩展到比喻意义，如缺乏经验。",
    "firstKnownUse": "Early 16th century",
    "relatedWords": [
      "vert",
      "virid",
      "verdure"
    ]
  },
  "difficultyAnalysis": {
    "overallLevel": "B2",
    "pronunciationDifficulty": "5",
    "spellingDifficulty": "4",
    "meaningComplexity": "6",
    "usageComplexity": "5",
    "learningTips": [
      "结合认知科学原理，将词汇与个人经历中的绿色景观联想；使用间隔重复法练习发音中的 /v/ 和 /r/ 音，以增强记忆巩固；针对中文母语学习者，建议通过视觉图像如照片来关联语义复杂度。"
    ]
  },
  "semanticRelations": {
    "synonyms": [
      {
        "word": "lush",
        "similarity": "0.8",
        "context": "用于描述茂盛植被的语境"
      },
      {
        "word": "green",
        "similarity": "0.7",
        "context": "在自然描述中的适用语境"
      }
    ],
    "antonyms": [
      {
        "word": "barren",
        "context": "用于描述贫瘠或无生机的土地语境"
      },
      {
        "word": "arid",
        "context": "在干燥环境或比喻缺乏经验的语境"
      }
    ],
    "hypernyms": [
      "green"
    ],
    "hyponyms": [],
    "collocations": [
      {
        "pattern": "verdant + noun (e.g., fields, hills, valleys)",
        "examples": [
          "verdant meadows",
          "verdant forests"
        ],
        "strength": "strong"
      },
      {
        "pattern": "in metaphorical expressions",
        "examples": [
          "a verdant mind"
        ],
        "strength": "weak"
      }
    ]
  },
  "culturalContext": {
    "culturalSignificance": "该词在英语文化中象征自然繁荣和田园诗意，常用于文学和艺术中隐含对环境美的赞颂；在跨文化语境中，可能与中文的 '绿意盎然' 类似，强调生态和谐。",
    "regionalVariations": [
      {
        "region": "United Kingdom",
        "variation": "更常用于乡村和历史文学描述",
        "usage": "在英国英语中，强调本土景观，如苏格兰高地"
      },
      {
        "region": "United States",
        "variation": "偶尔用于旅游推广或环境保护讨论",
        "usage": "在美国英语中，可能与本土自然保护区相关"
      }
    ],
    "historicalContext": "与欧洲文艺复兴时期的田园诗歌相关，常出现在莎士比亚等作家的作品中，反映工业革命前对自然的向往。",
    "modernUsage": "在当代社交媒体和环境议题中流行，如气候变化讨论中用于描述可持续生态。"
  },
  "memoryAids": {
    "visualScene": {
      "description": "想象一个郁郁葱葱的山谷，周围环绕着绿色草地和树木。",
      "keyElements": [
        "绿色草地",
        "茂盛树木",
        "山谷场景"
      ],
      "emotionalConnection": "联想到个人童年郊游的平静和喜悦，以触发情感记忆"
    },
    "mnemonicDevices": [
      {
        "type": "联想",
        "content": "Verdant 听起来像 'very dant'，联想为 'very green and abundant'",
        "explanation": "通过声音联想和视觉图像结合，强化词汇与颜色的认知连接。"
      },
      {
        "type": "缩略",
        "content": "V-E-R-D-A-N-T = Very Exciting Rich Dense And Natural Terrain",
        "explanation": "使用首字母缩略法创建故事，帮助记忆语义层面的复杂性。"
      }
    ],
    "wordAssociations": [
      "green",
      "lush",
      "forest",
      "naive"
    ]
  },
  "grammaticalInfo": {
    "irregularForms": {
      "plural": null,
      "pastTense": null,
      "pastParticiple": null,
      "presentParticiple": null,
      "comparative": "verdant (or verdanter in informal use)",
      "superlative": "verdanter (or verdantest)"
    },
    "syntacticPatterns": [
      {
        "pattern": "as a premodifier before a noun",
        "description": "用作定语修饰名词",
        "examples": [
          "a verdant garden"
        ]
      },
      {
        "pattern": "in predicate position",
        "description": "用作表语",
        "examples": [
          "The landscape is verdant"
        ]
      }
    ],
    "commonMistakes": [
      {
        "mistake": "Confusing with 'verdict'",
        "correction": "Verdant (adjective for green) vs. Verdict (noun for decision)",
        "explanation": "中文母语学习者可能因发音相似而混淆；建议通过语境区分。"
      },
      {
        "mistake": "Overusing in non-literal contexts",
        "correction": "Limit to appropriate figurative use",
        "explanation": "在中间水平学习者中，易将比喻义误用；强调语境练习。"
      }
    ]
  },
  "metadata": {
    "frequency": "Low (e.g., rank approximately 15,000 in COCA corpus)",
    "domains": [
      "Nature",
      "Literature",
      "Environment"
    ],
    "tags": [
      "Adjective",
      "Color",
      "Botany",
      "Figurative Language"
    ],
    "lastUpdated": "2023-10",
    "sources": [
      "OED (Oxford English Dictionary)",
      "Merriam-Webster",
      "COCA (Corpus of Contemporary American English)",
      "BNC (British National Corpus)"
    ]
  }
}